Workbook

Sheet START_HERE
A1: Hospice Branch Profitability Simulator
A2: Novice Control Panel
A4: Scenario Selection | F4: Instant Readout
A5: Selected Scenario | B5: Base
F6: Blended Revenue / Day | G6: =MIN(60,$B$9)/$B$9*$B$10 + MAX($B$9-60,0)/$B$9*$B$11 -> 208.72
F7: Total Variable Cost / Day | G7: =$B$12+$B$13+$B$14+$B$15+$B$16 -> 53
A8: Target ADC | B8: =VLOOKUP($B$5,Scenario_Assumptions!$A$2:$N$4,2,FALSE) -> 70 | D8: Set your expected average daily census. The model scales staffing and profit automatically. | F8: Contribution / Day | G8: =G6-G7 -> 155.72
A9: Average Length of Stay (days) | B9: =VLOOKUP($B$5,Scenario_Assumptions!$A$2:$N$4,3,FALSE) -> 90 | D9: Average number of days a patient remains on hospice. This drives admissions needed and blended revenue. | F9: Annual Fixed Payroll | G9: =SUM(Staffing_Assumptions!H2:H13) -> 2065000
A10: Days 1-60 Revenue / Day | B10: =VLOOKUP($B$5,Scenario_Assumptions!$A$2:$N$4,4,FALSE) -> 224.62 | D10: FY 2025 Routine Home Care rate for first 60 days. | F10: Annual Fixed Overhead | G10: =$B$17*12 -> 456000
A11: Days 61+ Revenue / Day | B11: =VLOOKUP($B$5,Scenario_Assumptions!$A$2:$N$4,5,FALSE) -> 176.92 | D11: FY 2025 Routine Home Care rate for day 61 and after. | F11: Annual Break Even Revenue | G11: =G9+G10 -> 2521000
A12: Pharmacy Cost / Day | B12: =VLOOKUP($B$5,Scenario_Assumptions!$A$2:$N$4,6,FALSE) -> 22 | D12: Average pharmacy spend per patient day. | F12: Break Even ADC | G12: =IF(G8<=0,"n/a",G11/(G8*365)) -> 44.354285
A13: DME Cost / Day | B13: =VLOOKUP($B$5,Scenario_Assumptions!$A$2:$N$4,7,FALSE) -> 10 | D13: Average DME spend per patient day. | F13: ADC for Target Margin | G13: =IF((1-$B$19)*G6-G7<=0,"n/a",G11/(((1-$B$19)*G6-G7)*365)) -> 53.713684
A14: Supplies Cost / Day | B14: =VLOOKUP($B$5,Scenario_Assumptions!$A$2:$N$4,8,FALSE) -> 10 | D14: Average supplies spend per patient day. | F14: Admissions Needed / Month | G14: =$B$8/$B$9*30 -> 23.333333
A15: Travel Cost / Day | B15: =VLOOKUP($B$5,Scenario_Assumptions!$A$2:$N$4,9,FALSE) -> 6 | D15: Mileage, fuel, and travel spend per patient day. | F15: Marketers Needed | G15: =ROUNDUP(G14/$B$20,0) -> 3
A16: Other Variable Cost / Day | B16: =VLOOKUP($B$5,Scenario_Assumptions!$A$2:$N$4,10,FALSE) -> 5 | D16: Other variable clinical cost per patient day.
A17: Monthly Fixed Overhead | B17: =VLOOKUP($B$5,Scenario_Assumptions!$A$2:$N$4,11,FALSE) -> 38000 | D17: Office, insurance, EMR, liability, phones, rent, and admin overhead per month.
A18: Cash on Hand at Start | B18: =VLOOKUP($B$5,Scenario_Assumptions!$A$2:$N$4,12,FALSE) -> 250000 | D18: Starting cash for the startup ramp and monthly burn analysis.
A19: Target Margin | B19: =VLOOKUP($B$5,Scenario_Assumptions!$A$2:$N$4,13,FALSE) -> 0.13 | D19: Target operating margin used to solve target ADC.
A20: Admissions per Marketer / Month | B20: =VLOOKUP($B$5,Scenario_Assumptions!$A$2:$N$4,14,FALSE) -> 8 | D20: How many admissions one marketer can produce each month on average.
A21: RN Caseload per RN | B21: 15 | D21: Patients per RN case manager.
A22: Aide Caseload per Aide | B22: 12 | D22: Patients per hospice aide.
A23: Social Worker Caseload | B23: 35 | D23: Patients per social worker.
A24: Chaplain Caseload | B24: 55 | D24: Patients per chaplain.

Sheet Scenario_Assumptions
A1: Scenario | B1: Target ADC | C1: LOS Days | D1: RHC Day 1-60 | E1: RHC Day 61+ | F1: Pharmacy/Day | G1: DME/Day | H1: Supplies/Day | I1: Travel/Day | J1: Other/Day | K1: Monthly Overhead | L1: Start Cash | M1: Target Margin | N1: Admissions/Marketer
A2: Lean | B2: 60 | C2: 95 | D2: 224.62 | E2: 176.92 | F2: 16 | G2: 8 | H2: 9 | I2: 5 | J2: 4 | K2: 32000 | L2: 250000 | M2: 0.13 | N2: 10
A3: Base | B3: 70 | C3: 90 | D3: 224.62 | E3: 176.92 | F3: 22 | G3: 10 | H3: 10 | I3: 6 | J3: 5 | K3: 38000 | L3: 250000 | M3: 0.13 | N3: 8
A4: High Acuity | B4: 80 | C4: 75 | D4: 224.62 | E4: 176.92 | F4: 38 | G4: 15 | H4: 12 | I4: 7 | J4: 8 | K4: 42000 | L4: 250000 | M4: 0.13 | N4: 7

Sheet Staffing_Assumptions
A1: Role | B1: Annual Salary | C1: Minimum FTE | D1: Caseload Trigger | E1: Auto FTE | F1: Chosen FTE | G1: Monthly Cost | H1: Annual Cost
A2: Executive Director | B2: 140000 | C2: 1 | D2: 9999 | E2: =C2 -> 1 | F2: =MAX(C2,E2) -> 1 | G2: =B2*F2/12 -> 11666.667 | H2: =B2*F2 -> 140000
A3: Supervisor RN Case Manager | B3: 110000 | C3: 1 | D3: 9999 | E3: =C3 -> 1 | F3: =MAX(C3,E3) -> 1 | G3: =B3*F3/12 -> 9166.6667 | H3: =B3*F3 -> 110000
A4: RN Case Manager | B4: 100000 | C4: 3 | D4: =START_HERE!$B$21 -> 15 | E4: =ROUNDUP(START_HERE!$B$8/START_HERE!$B$21,0) -> 5 | F4: =MAX(C4,E4) -> 5 | G4: =B4*F4/12 -> 41666.667 | H4: =B4*F4 -> 500000
A5: Hospice Aide | B5: 50000 | C5: 6 | D5: =START_HERE!$B$22 -> 12 | E5: =ROUNDUP(START_HERE!$B$8/START_HERE!$B$22,0) -> 6 | F5: =MAX(C5,E5) -> 6 | G5: =B5*F5/12 -> 25000 | H5: =B5*F5 -> 300000
A6: Social Worker | B6: 75000 | C6: 2 | D6: =START_HERE!$B$23 -> 35 | E6: =ROUNDUP(START_HERE!$B$8/START_HERE!$B$23,0) -> 2 | F6: =MAX(C6,E6) -> 2 | G6: =B6*F6/12 -> 12500 | H6: =B6*F6 -> 150000
A7: Chaplain | B7: 70000 | C7: 1 | D7: =START_HERE!$B$24 -> 55 | E7: =ROUNDUP(START_HERE!$B$8/START_HERE!$B$24,0) -> 2 | F7: =MAX(C7,E7) -> 2 | G7: =B7*F7/12 -> 11666.667 | H7: =B7*F7 -> 140000
A8: After Hours RN | B8: 95000 | C8: 1 | D8: 9999 | E8: =C8 -> 1 | F8: =MAX(C8,E8) -> 1 | G8: =B8*F8/12 -> 7916.6667 | H8: =B8*F8 -> 95000
A9: Weekend RN | B9: 95000 | C9: 1 | D9: 9999 | E9: =C9 -> 1 | F9: =MAX(C9,E9) -> 1 | G9: =B9*F9/12 -> 7916.6667 | H9: =B9*F9 -> 95000
A10: Intake Coordinator | B10: 60000 | C10: 1 | D10: 9999 | E10: =C10 -> 1 | F10: =MAX(C10,E10) -> 1 | G10: =B10*F10/12 -> 5000 | H10: =B10*F10 -> 60000
A11: Secretary | B11: 55000 | C11: 1 | D11: 9999 | E11: =C11 -> 1 | F11: =MAX(C11,E11) -> 1 | G11: =B11*F11/12 -> 4583.3333 | H11: =B11*F11 -> 55000
A12: Sales Rep / Marketer | B12: 115000 | C12: 2 | D12: =START_HERE!$B$20 -> 8 | E12: =ROUNDUP(START_HERE!$G$14/START_HERE!$B$20,0) -> 3 | F12: =MAX(C12,E12) -> 3 | G12: =B12*F12/12 -> 28750 | H12: =B12*F12 -> 345000
A13: Medical Director Contract | B13: 75000 | C13: 1 | D13: 9999 | E13: =C13 -> 1 | F13: =MAX(C13,E13) -> 1 | G13: =B13*F13/12 -> 6250 | H13: =B13*F13 -> 75000
A14: Total | G14: =SUM(G2:G13) -> 172083.33 | H14: =SUM(H2:H13) -> 2065000

Sheet Admissions_Engine
A1: Admissions Engine
A3: Metric | B3: Value | C3: How to use this
A4: Target ADC | B4: =START_HERE!$B$8 -> 70 | C4: Desired average daily census.
A5: Average Length of Stay | B5: =START_HERE!$B$9 -> 90 | C5: Average days a patient remains on service.
A6: Admissions Needed / Month | B6: =START_HERE!$G$14 -> 23.333333 | C6: Monthly admissions needed to replace turnover and hold census.
A7: Admissions / Marketer / Month | B7: =START_HERE!$B$20 -> 8 | C7: Expected monthly admissions per marketer.
A8: Marketers Needed | B8: =START_HERE!$G$15 -> 3 | C8: Auto-solved number of marketers needed to sustain admissions.
A9: Current Marketers in Staffing Tab | B9: =INDEX(Staffing_Assumptions!F:F,MATCH("Sales Rep / Marketer",Staffing_Assumptions!A:A,0)) -> 3 | C9: Pulled from staffing assumptions.
A10: Admissions Gap / Surplus | B10: =B8*B7-B6 -> 0.66666667 | C10: Positive means marketer capacity exceeds need. Negative means a gap.

Sheet Profit_Simulator
A1: ADC | B1: Revenue/Day | C1: Var Cost/Day | D1: Annual Revenue | E1: Annual Variable Cost | F1: Annual Fixed Cost | G1: Annual Profit | H1: Margin | I1: Status
A2: 10 | B2: =START_HERE!$G$6 -> 208.72 | C2: =START_HERE!$G$7 -> 53 | D2: =A2*B2*365 -> 761828 | E2: =A2*C2*365 -> 193450 | F2: =START_HERE!$G$9+START_HERE!$G$10 -> 2521000 | G2: =D2-E2-F2 -> -1952622 | H2: =IF(D2=0,0,G2/D2) -> -2.5630746 | I2: =IF(G2<0,"Below break even",IF(H2<START_HERE!$B$19,"Profitable but below target","At or above target")) -> Below break even
A3: 11 | B3: =START_HERE!$G$6 -> 208.72 | C3: =START_HERE!$G$7 -> 53 | D3: =A3*B3*365 -> 838010.8 | E3: =A3*C3*365 -> 212795 | F3: =START_HERE!$G$9+START_HERE!$G$10 -> 2521000 | G3: =D3-E3-F3 -> -1895784.2 | H3: =IF(D3=0,0,G3/D3) -> -2.2622432 | I3: =IF(G3<0,"Below break even",IF(H3<START_HERE!$B$19,"Profitable but below target","At or above target")) -> Below break even
A4: 12 | B4: =START_HERE!$G$6 -> 208.72 | C4: =START_HERE!$G$7 -> 53 | D4: =A4*B4*365 -> 914193.6 | E4: =A4*C4*365 -> 232140 | F4: =START_HERE!$G$9+START_HERE!$G$10 -> 2521000 | G4: =D4-E4-F4 -> -1838946.4 | H4: =IF(D4=0,0,G4/D4) -> -2.0115503 | I4: =IF(G4<0,"Below break even",IF(H4<START_HERE!$B$19,"Profitable but below target","At or above target")) -> Below break even
A5: 13 | B5: =START_HERE!$G$6 -> 208.72 | C5: =START_HERE!$G$7 -> 53 | D5: =A5*B5*365 -> 990376.4 | E5: =A5*C5*365 -> 251485 | F5: =START_HERE!$G$9+START_HERE!$G$10 -> 2521000 | G5: =D5-E5-F5 -> -1782108.6 | H5: =IF(D5=0,0,G5/D5) -> -1.7994256 | I5: =IF(G5<0,"Below break even",IF(H5<START_HERE!$B$19,"Profitable but below target","At or above target")) -> Below break even
A6: 14 | B6: =START_HERE!$G$6 -> 208.72 | C6: =START_HERE!$G$7 -> 53 | D6: =A6*B6*365 -> 1066559.2 | E6: =A6*C6*365 -> 270830 | F6: =START_HERE!$G$9+START_HERE!$G$10 -> 2521000 | G6: =D6-E6-F6 -> -1725270.8 | H6: =IF(D6=0,0,G6/D6) -> -1.6176043 | I6: =IF(G6<0,"Below break even",IF(H6<START_HERE!$B$19,"Profitable but below target","At or above target")) -> Below break even
A7: 15 | B7: =START_HERE!$G$6 -> 208.72 | C7: =START_HERE!$G$7 -> 53 | D7: =A7*B7*365 -> 1142742 | E7: =A7*C7*365 -> 290175 | F7: =START_HERE!$G$9+START_HERE!$G$10 -> 2521000 | G7: =D7-E7-F7 -> -1668433 | H7: =IF(D7=0,0,G7/D7) -> -1.460026 | I7: =IF(G7<0,"Below break even",IF(H7<START_HERE!$B$19,"Profitable but below target","At or above target")) -> Below break even
A8: 16 | B8: =START_HERE!$G$6 -> 208.72 | C8: =START_HERE!$G$7 -> 53 | D8: =A8*B8*365 -> 1218924.8 | E8: =A8*C8*365 -> 309520 | F8: =START_HERE!$G$9+START_HERE!$G$10 -> 2521000 | G8: =D8-E8-F8 -> -1611595.2 | H8: =IF(D8=0,0,G8/D8) -> -1.3221449 | I8: =IF(G8<0,"Below break even",IF(H8<START_HERE!$B$19,"Profitable but below target","At or above target")) -> Below break even
A9: 17 | B9: =START_HERE!$G$6 -> 208.72 | C9: =START_HERE!$G$7 -> 53 | D9: =A9*B9*365 -> 1295107.6 | E9: =A9*C9*365 -> 328865 | F9: =START_HERE!$G$9+START_HERE!$G$10 -> 2521000 | G9: =D9-E9-F9 -> -1554757.4 | H9: =IF(D9=0,0,G9/D9) -> -1.2004851 | I9: =IF(G9<0,"Below break even",IF(H9<START_HERE!$B$19,"Profitable but below target","At or above target")) -> Below break even
A10: 18 | B10: =START_HERE!$G$6 -> 208.72 | C10: =START_HERE!$G$7 -> 53 | D10: =A10*B10*365 -> 1371290.4 | E10: =A10*C10*365 -> 348210 | F10: =START_HERE!$G$9+START_HERE!$G$10 -> 2521000 | G10: =D10-E10-F10 -> -1497919.6 | H10: =IF(D10=0,0,G10/D10) -> -1.0923431 | I10: =IF(G10<0,"Below break even",IF(H10<START_HERE!$B$19,"Profitable but below target","At or above target")) -> Below break even
A11: 19 | B11: =START_HERE!$G$6 -> 208.72 | C11: =START_HERE!$G$7 -> 53 | D11: =A11*B11*365 -> 1447473.2 | E11: =A11*C11*365 -> 367555 | F11: =START_HERE!$G$9+START_HERE!$G$10 -> 2521000 | G11: =D11-E11-F11 -> -1441081.8 | H11: =IF(D11=0,0,G11/D11) -> -0.99558444 | I11: =IF(G11<0,"Below break even",IF(H11<START_HERE!$B$19,"Profitable but below target","At or above target")) -> Below break even
A12: 20 | B12: =START_HERE!$G$6 -> 208.72 | C12: =START_HERE!$G$7 -> 53 | D12: =A12*B12*365 -> 1523656 | E12: =A12*C12*365 -> 386900 | F12: =START_HERE!$G$9+START_HERE!$G$10 -> 2521000 | G12: =D12-E12-F12 -> -1384244 | H12: =IF(D12=0,0,G12/D12) -> -0.90850166 | I12: =IF(G12<0,"Below break even",IF(H12<START_HERE!$B$19,"Profitable but below target","At or above target")) -> Below break even
A13: 21 | B13: =START_HERE!$G$6 -> 208.72 | C13: =START_HERE!$G$7 -> 53 | D13: =A13*B13*365 -> 1599838.8 | E13: =A13*C13*365 -> 406245 | F13: =START_HERE!$G$9+START_HERE!$G$10 -> 2521000 | G13: =D13-E13-F13 -> -1327406.2 | H13: =IF(D13=0,0,G13/D13) -> -0.82971247 | I13: =IF(G13<0,"Below break even",IF(H13<START_HERE!$B$19,"Profitable but below target","At or above target")) -> Below break even
... A192: 200 | B192: =START_HERE!$G$6 -> 208.72 | C192: =START_HERE!$G$7 -> 53 | D192: =A192*B192*365 -> 15236560 | E192: =A192*C192*365 -> 3869000 | F192: =START_HERE!$G$9+START_HERE!$G$10 -> 2521000 | G192: =D192-E192-F192 -> 8846560 | H192: =IF(D192=0,0,G192/D192) -> 0.580614 | I192: =IF(G192<0,"Below break even",IF(H192<START_HERE!$B$19,"Profitable but below target","At or above target")) -> At or above target

Sheet Dashboard
A1: Dashboard
A4: Selected Scenario | B4: =START_HERE!$B$5 -> Base | D4: Admissions Needed / Month | E4: =START_HERE!$G$14 -> 23.333333 | G4: Revenue / Patient Day | H4: =START_HERE!$G$6 -> 208.72
A5: Target ADC | B5: =START_HERE!$B$8 -> 70 | D5: Marketers Needed | E5: =START_HERE!$G$15 -> 3 | G5: Variable Cost / Patient Day | H5: =START_HERE!$G$7 -> 53
A6: Break Even ADC | B6: =START_HERE!$G$12 -> 44.354285 | D6: Annual Fixed Payroll | E6: =START_HERE!$G$9 -> 2065000 | G6: Contribution / Patient Day | H6: =START_HERE!$G$8 -> 155.72
A7: ADC for Target Margin | B7: =START_HERE!$G$13 -> 53.713684 | D7: Annual Fixed Overhead | E7: =START_HERE!$G$10 -> 456000 | G7: Target Margin | H7: =START_HERE!$B$19 -> 0.13

Sheet How_to_Use
A1: How to Use This Model
A3: 1. Go to START_HERE and choose Lean, Base, or High Acuity in cell B5.
A4: 2. Edit blue input cells only. Those are the safe control cells for a novice user.
A5: 3. Read the green output cells on the right to see break even ADC, admissions needed, and target margin ADC.
A6: 4. Open Staffing_Assumptions to see exactly how many staff are required at the current ADC. The model enforces minimum staffing floors and auto-adds staff when caseload ratios are exceeded.
A7: 5. Open Admissions_Engine to see how many admissions per month you need and how many marketers are required.
A8: 6. Open Profit_Simulator to see profit and margin from ADC 10 through 200.
A9: 7. Open Dashboard for charts and a one-page management summary.
A10: 8. If you want to build inside the workbook, copy an existing formula row rather than typing over formulas. Blue cells are inputs. Green cells are key outputs. Dark blue headers identify sections.
A11: Three operational levers:
A12: A. Census density: fixed overhead is spread over more patients as ADC rises, which drives margin expansion.
A13: B. Length of stay discipline: the first 60 days pay more than day 61 and after, so LOS mix changes blended revenue.
A14: C. Clinical cost management: pharmacy, DME, travel, and staffing efficiency determine whether margin holds or collapses.
